durham_directory/__init__.py
durham_directory-1.3.0.dist-info/entry_points.txt
durham_directory-1.3.0.dist-info/LICENSE
durham_directory-1.3.0.dist-info/WHEEL
durham_directory-1.3.0.dist-info/METADATA
durham_directory-1.3.0.dist-info/RECORD
